odoo/addons/partner_contact_personal_information_page/README.rst
odoo/addons/partner_contact_personal_information_page/__init__.py
odoo/addons/partner_contact_personal_information_page/__manifest__.py
odoo/addons/partner_contact_personal_information_page/i18n/de.po
odoo/addons/partner_contact_personal_information_page/i18n/en.po
odoo/addons/partner_contact_personal_information_page/i18n/es.po
odoo/addons/partner_contact_personal_information_page/i18n/fi.po
odoo/addons/partner_contact_personal_information_page/i18n/fr.po
odoo/addons/partner_contact_personal_information_page/i18n/hr_HR.po
odoo/addons/partner_contact_personal_information_page/i18n/it.po
odoo/addons/partner_contact_personal_information_page/i18n/nl.po
odoo/addons/partner_contact_personal_information_page/i18n/pt_BR.po
odoo/addons/partner_contact_personal_information_page/i18n/pt_PT.po
odoo/addons/partner_contact_personal_information_page/i18n/sl.po
odoo/addons/partner_contact_personal_information_page/static/description/icon.png
odoo/addons/partner_contact_personal_information_page/views/res_partner.xml
odoo11_addon_partner_contact_personal_information_page-11.0.1.0.0.dist-info/DESCRIPTION.rst
odoo11_addon_partner_contact_personal_information_page-11.0.1.0.0.dist-info/METADATA
odoo11_addon_partner_contact_personal_information_page-11.0.1.0.0.dist-info/RECORD
odoo11_addon_partner_contact_personal_information_page-11.0.1.0.0.dist-info/WHEEL
odoo11_addon_partner_contact_personal_information_page-11.0.1.0.0.dist-info/metadata.json
odoo11_addon_partner_contact_personal_information_page-11.0.1.0.0.dist-info/top_level.txt
